cubicweb/__init__.py
cubicweb/__main__.py
cubicweb/__pkginfo__.py
cubicweb/_exceptions.py
cubicweb/_gcdebug.py
cubicweb/appobject.py
cubicweb/crypto.py
cubicweb/cwconfig.py
cubicweb/cwctl.py
cubicweb/cwgettext.py
cubicweb/cwvreg.py
cubicweb/debug.py
cubicweb/entity.py
cubicweb/i18n.py
cubicweb/mail.py
cubicweb/md5crypt.py
cubicweb/migration.py
cubicweb/mttransforms.py
cubicweb/multipart.py
cubicweb/predicates.py
cubicweb/pytestconf.py
cubicweb/rdf.py
cubicweb/repoapi.py
cubicweb/req.py
cubicweb/rqlrewrite.py
cubicweb/rqlsuggestions.py
cubicweb/rset.py
cubicweb/rtags.py
cubicweb/schema.py
cubicweb/schema_exporters.py
cubicweb/toolsutils.py
cubicweb/transaction.py
cubicweb/uilib.py
cubicweb/utils.py
cubicweb/wfutils.py
cubicweb/xy.py
cubicweb/dataimport/__init__.py
cubicweb/dataimport/csv.py
cubicweb/dataimport/importer.py
cubicweb/dataimport/massive_store.py
cubicweb/dataimport/pgstore.py
cubicweb/dataimport/stores.py
cubicweb/dataimport/test/test_csv.py
cubicweb/dataimport/test/test_massive_store.py
cubicweb/dataimport/test/test_pgstore.py
cubicweb/dataimport/test/test_stores.py
cubicweb/dataimport/test/unittest_importer.py
cubicweb/dataimport/test/data/geonames.csv
cubicweb/dataimport/test/data/people.csv
cubicweb/dataimport/test/data/schema.py
cubicweb/dataimport/test/data/timeZones.txt
cubicweb/dataimport/test/data-massimport/schema.py
cubicweb/devtools/__init__.py
cubicweb/devtools/apptest_config.py
cubicweb/devtools/devctl.py
cubicweb/devtools/fake.py
cubicweb/devtools/fill.py
cubicweb/devtools/fix_po_encoding
cubicweb/devtools/htmlparser.py
cubicweb/devtools/httptest.py
cubicweb/devtools/instrument.py
cubicweb/devtools/realdbtest.py
cubicweb/devtools/repotest.py
cubicweb/devtools/stresstester.py
cubicweb/devtools/testlib.py
cubicweb/devtools/data/cwmock.js
cubicweb/devtools/data/qunit.css
cubicweb/devtools/data/qunit.js
cubicweb/devtools/test/unittest_dbfill.py
cubicweb/devtools/test/unittest_devctl.py
cubicweb/devtools/test/unittest_fill.py
cubicweb-5.0.1.dist-info/licenses/COPYING
cubicweb-5.0.1.dist-info/licenses/COPYING.LESSER
cubicweb-5.0.1.dist-info/METADATA
cubicweb-5.0.1.dist-info/WHEEL
cubicweb-5.0.1.dist-info/entry_points.txt
cubicweb-5.0.1.dist-info/top_level.txt
cubicweb-5.0.1.dist-info/RECORD
