Metadata-Version: 2.4
Name: cubicweb
Version: 5.0.1
Summary: a repository of entities / relations for knowledge management
Author-email: Logilab <contact@logilab.fr>
License: GNU Lesser General Public License v2 or later (LGPLv2+)
Project-URL: Documentation, https://cubicweb.readthedocs.io/
Project-URL: Issues, https://forge.extranet.logilab.fr/cubicweb/cubicweb/-/issues
Project-URL: Repository, https://forge.extranet.logilab.fr/cubicweb/cubicweb
Project-URL: Website, https://www.cubicweb.org
Classifier: Environment :: Web Environment
Classifier: Framework :: CubicWeb
Classifier: Programming Language :: Python
Classifier: Programming Language :: Python :: 3
Classifier: Programming Language :: Python :: 3 :: Only
Classifier: Programming Language :: JavaScript
Requires-Python: >=3.11
License-File: COPYING
License-File: COPYING.LESSER
Requires-Dist: cachetools>=5.5.1
Requires-Dist: filelock>=3.17.0
Requires-Dist: logilab-common<3.0.0,>=2.1.0
Requires-Dist: logilab-database<3.0.0,>=2.0.0
Requires-Dist: logilab-mtconverter<2.0.0,>=1.0.0
Requires-Dist: lxml<6.0.0,>=5.2.0
Requires-Dist: lxml_html_clean>=0.4.1
Requires-Dist: Markdown>=3.7
Requires-Dist: passlib>=1.7.4
Requires-Dist: pyramid<2.0.0,>=1.10.8
Requires-Dist: pyramid_multiauth<1.0.0
Requires-Dist: pytz
Requires-Dist: rdflib>=7.1.3
Requires-Dist: repoze.lru
Requires-Dist: rql<2.0.0,>=1.0.2
Requires-Dist: waitress<4.0.0,>=3.0.2
Requires-Dist: wsgicors>=0.7.0
Requires-Dist: yams>=2.0.0
Provides-Extra: captcha
Requires-Dist: Pillow>=11.1.0; extra == "captcha"
Provides-Extra: crypto
Requires-Dist: pycryptodomex>=3.21.0; extra == "crypto"
Provides-Extra: ext
Requires-Dist: docutils>=0.21.2; extra == "ext"
Provides-Extra: ical
Requires-Dist: vobject>=0.9.9; extra == "ical"
Provides-Extra: postgresql
Requires-Dist: psycopg2-binary>=2.9.10; extra == "postgresql"
Provides-Extra: s3
Requires-Dist: minio>=7.2.15; extra == "s3"
Dynamic: license-file
